jserpy/__init__.py
jserpy/json_handler.py
jserpy/json_handler_utils.py
jserpy/json_typing.py
jserpy/jsonable.py
tests/test_jserpy.py
jserpy-0.1.3.dist-info/LICENSE
jserpy-0.1.3.dist-info/METADATA
jserpy-0.1.3.dist-info/WHEEL
jserpy-0.1.3.dist-info/top_level.txt
jserpy-0.1.3.dist-info/RECORD
