Metadata-Version: 2.2
Name: jserpy
Version: 0.1.3
Summary: A Python library for serializing and deserializing complex objects to and from JSON
Author-email: Ron Pick <ronpi1310@gmail.com>
Project-URL: Homepage, https://github.com/ronpik/jserpy
Project-URL: Bug Tracker, https://github.com/ronpik/jserpy/issues
Classifier: Programming Language :: Python :: 3
Classifier: License :: OSI Approved :: MIT License
Classifier: Operating System :: OS Independent
Requires-Python: >=3.10
License-File: LICENSE
Requires-Dist: typing-inspect>=0.9.0
Requires-Dist: numpy>=1.13.0
